mane/__init__.py
mane/logging.py
langchain_mane-0.0.2.dist-info/METADATA
langchain_mane-0.0.2.dist-info/WHEEL
langchain_mane-0.0.2.dist-info/top_level.txt
langchain_mane-0.0.2.dist-info/RECORD
