Metadata-Version: 2.1
Name: langchain-mane
Version: 0.0.2
Summary: PYPI
Home-page: https://github.com/teddylee777/teddynote
Author: mane5880
Author-email: gjtjqkr5880@gmail.com
Keywords: langchain,mane,python langchain,langchain util
Requires-Python: >=3.8
